ruclogin/__init__.py
ruclogin/config.ini
ruclogin/ruclogin.py
ruclogin-0.3.3.dist-info/LICENSE
ruclogin-0.3.3.dist-info/METADATA
ruclogin-0.3.3.dist-info/WHEEL
ruclogin-0.3.3.dist-info/entry_points.txt
ruclogin-0.3.3.dist-info/top_level.txt
ruclogin-0.3.3.dist-info/RECORD
