Metadata-Version: 2.2
Name: ruclogin
Version: 0.3.3
Summary: Login to *.ruc.edu.cn, get cookies.
Author-email: panjd123 <xm.jarden@gmail.com>
License: MIT License
Project-URL: Homepage, https://github.com/panjd123/ruclogin
Project-URL: Repository, https://github.com/panjd123/ruclogin.git
Requires-Python: <3.13
License-File: LICENSE
Requires-Dist: requests
Requires-Dist: selenium
Requires-Dist: selenium-wire
Requires-Dist: webdriver_manager
Requires-Dist: ddddocr>=1.5.6
Requires-Dist: blinker==1.7.0
